s2_ai_tools/__init__.py
s2_ai_tools/config.py
s2_ai_tools/definitions.py
s2_ai_tools/tools.py
s2_ai_tools-1.0.6.dist-info/LICENSE
s2_ai_tools-1.0.6.dist-info/METADATA
s2_ai_tools-1.0.6.dist-info/WHEEL
s2_ai_tools-1.0.6.dist-info/top_level.txt
s2_ai_tools-1.0.6.dist-info/RECORD
