Metadata-Version: 2.1
Name: s2_ai_tools
Version: 1.0.6
Summary: Singlestore tools definitions
Home-page: https://github.com/singlestore-labs/singlestore-ai-tools
Author: Singlestore
Author-email: support@singlestore.com
Classifier: Programming Language :: Python :: 3
Classifier: License :: OSI Approved :: MIT License
Classifier: Operating System :: OS Independent
Requires-Python: >=3.10
License-File: LICENSE
Requires-Dist: requests
Requires-Dist: singlestoredb
Requires-Dist: python-dotenv
